afterglow/__init__.py
afterglow/__main__.py
afterglow/argparser.py
afterglow/child.py
afterglow/files.py
afterglow/message.py
afterglow/parent.py
afterglow-0.1.0.dev0.dist-info/LICENSE
afterglow-0.1.0.dev0.dist-info/METADATA
afterglow-0.1.0.dev0.dist-info/WHEEL
afterglow-0.1.0.dev0.dist-info/RECORD
