Metadata-Version: 2.1
Name: afterglow
Version: 0.1.0.dev0
Summary: A configuration tool for ignition based systems
Author: James
Author-email: james@dataligand.com
Requires-Python: >=3.11,<4.0
Classifier: Programming Language :: Python :: 3
Classifier: Programming Language :: Python :: 3.11
Requires-Dist: asyncssh (>=2.13.1,<3.0.0)
Requires-Dist: bcrypt (>=4.0.1,<5.0.0)
Requires-Dist: structlog (>=23.1.0,<24.0.0)
